{
  "project_info": {
    "project_number": "159786187008",
    "project_id": "mizdah-6f815",
    "storage_bucket": "mizdah-6f815.appspot.com"
  },
  "client": [
    {
      "client_info": {
        "mobilesdk_app_id": "1:159786187008:android:5c8385987de2e824cadbe5",
        "android_client_info": {
          "package_name": "com.ogoul.mizdah"
        }
      },
      "oauth_client": [
        {
          "client_id": "159786187008-8ft0tage4pk99spsr64oocarkb28iivj.apps.googleusercontent.com",
          "client_type": 3
        }
      ],
      "api_key": [
        {
          "current_key": "AIzaSyBTyyr0zl1TpaswUBHNGBhkle05NRdq7u8"
        }
      ],
      "services": {
        "appinvite_service": {
          "other_platform_oauth_client": [
            {
              "client_id": "159786187008-8ft0tage4pk99spsr64oocarkb28iivj.apps.googleusercontent.com",
              "client_type": 3
            }
          ]
        }
      }
    }
  ],
  "configuration_version": "1"
}